boto3_utils_layer/__init__.py
boto3_utils_layer/utils.py
boto3_utils_layer-1.0.dist-info/METADATA
boto3_utils_layer-1.0.dist-info/WHEEL
boto3_utils_layer-1.0.dist-info/top_level.txt
boto3_utils_layer-1.0.dist-info/RECORD
