Metadata-Version: 2.1
Name: boto3-utils-layer
Version: 1.0
Summary: Boto3 utils for lambda layer.
Author: Pratima Chettri
Author-email: chettripratima@gmail.com
License: UNKNOWN
Platform: UNKNOWN
Requires-Dist: boto3
